thothglyph/__init__.py
thothglyph/app/__init__.py
thothglyph/app/converter.py
thothglyph/data/tglyph.svg
thothglyph/data/tglyph_256.png
thothglyph/data/tglyph_64.png
thothglyph/error.py
thothglyph/ext/blockdiag.py
thothglyph/ext/graphviz.py
thothglyph/ext/math.py
thothglyph/ext/mermaid.py
thothglyph/ext/plantuml.py
thothglyph/ext/wavedrom.py
thothglyph/node/logging.py
thothglyph/node/nd.py
thothglyph/reader/__init__.py
thothglyph/reader/md.py
thothglyph/reader/reader.py
thothglyph/reader/tglyph.py
thothglyph/template/common/check_dis.pdf
thothglyph/template/common/check_dis.svg
thothglyph/template/common/check_en.pdf
thothglyph/template/common/check_en.svg
thothglyph/template/common/check_im.pdf
thothglyph/template/common/check_im.svg
thothglyph/template/docx/default/style.docx
thothglyph/template/html/default/index.html
thothglyph/template/html/preview/index.html
thothglyph/template/latex/default/document-ja.tex
thothglyph/util/svg.py
thothglyph/writer/__init__.py
thothglyph/writer/docx.py
thothglyph/writer/html.py
thothglyph/writer/latex.py
thothglyph/writer/pdf.py
thothglyph/writer/writer.py
thothglyph_doc-0.2.9.dist-info/LICENSE
thothglyph_doc-0.2.9.dist-info/METADATA
thothglyph_doc-0.2.9.dist-info/WHEEL
thothglyph_doc-0.2.9.dist-info/entry_points.txt
thothglyph_doc-0.2.9.dist-info/RECORD
