Metadata-Version: 2.3
Name: thothglyph-doc
Version: 0.2.9
Summary: A Documentation converter and language for Engineers
License: MIT
Author: nakandev
Author-email: nakandev.s@gmail.com
Requires-Python: >=3.8,<4.0
Classifier: License :: OSI Approved :: MIT License
Classifier: Programming Language :: Python :: 3
Classifier: Programming Language :: Python :: 3.8
Classifier: Programming Language :: Python :: 3.9
Classifier: Programming Language :: Python :: 3.10
Classifier: Programming Language :: Python :: 3.11
Classifier: Programming Language :: Python :: 3.12
Classifier: Programming Language :: Python :: 3.13
Requires-Dist: cairosvg (>=2.5.2,<3.0.0)
Requires-Dist: markdown-it-py[plugins] (>=3.0.0,<4.0.0)
Requires-Dist: pillow (>=9.2.0,<10.0.0)
Requires-Dist: pyyaml (>=6.0.2,<7.0.0)
